snowflake_css/__init__.py
snowflake_css/__main__.py
snowflake_css/compiler.py
snowflake_css/demo.py
snowflake_css/globals.scss
snowflake_css/components/base/demo.html
snowflake_css/components/base/style.scss
snowflake_css/components/button/demo.html
snowflake_css/components/button/style.scss
snowflake_css/components/footer/demo.html
snowflake_css/components/footer/style.scss
snowflake_css/components/inline-list/demo.html
snowflake_css/components/inline-list/style.scss
snowflake_css/components/navbar/demo.html
snowflake_css/components/navbar/style.scss
snowflake_css/components/pygments-theme/demo.html
snowflake_css/components/pygments-theme/style.scss
snowflake_css/components/sidebar/demo.html
snowflake_css/components/sidebar/style.scss
snowflake_css/components/typography/demo.html
snowflake_css/components/typography/style.scss
snowflake_css/components/vertical-fill/demo.html
snowflake_css/components/vertical-fill/style.scss
snowflake_css/demo/template.html
snowflake_css-1.3.2.dist-info/DESCRIPTION.rst
snowflake_css-1.3.2.dist-info/METADATA
snowflake_css-1.3.2.dist-info/RECORD
snowflake_css-1.3.2.dist-info/WHEEL
snowflake_css-1.3.2.dist-info/entry_points.txt
snowflake_css-1.3.2.dist-info/metadata.json
snowflake_css-1.3.2.dist-info/top_level.txt
