Metadata-Version: 2.0
Name: snowflake-css
Version: 1.3.2
Summary: My personal CSS components collection
Home-page: https://github.com/pietroalbini/snowflake-css
Author: Pietro Albini
Author-email: pietro@pietroalbini.org
License: GNU-GPL v3+
Platform: UNKNOWN
Classifier: Development Status :: 5 - Production/Stable
Classifier: Environment :: Web Environment
Classifier: Intended Audience :: Developers
Classifier: License :: OSI Approved :: MIT License
Requires-Dist: pyscss
Requires-Dist: rcssmin
Provides-Extra: demo
Requires-Dist: jinja2; extra == 'demo'
Requires-Dist: django-htmlmin; extra == 'demo'
